sandipan/__init__.py
sandipan/__main__.py
sandipan/me.py
sandipan-0.0.10.dist-info/LICENSE
sandipan-0.0.10.dist-info/METADATA
sandipan-0.0.10.dist-info/WHEEL
sandipan-0.0.10.dist-info/top_level.txt
sandipan-0.0.10.dist-info/RECORD
