Metadata-Version: 2.1
Name: sandipan
Version: 0.0.10
Summary: Take it Easy; Make it Easy;
Home-page: https://sandipan.ml
Author: Sandipan Roy
Author-email: me@sandipan.ml
License: MIT
Platform: UNKNOWN
Classifier: Development Status :: 4 - Beta
Classifier: License :: OSI Approved :: MIT License
Classifier: Programming Language :: Python
Classifier: Programming Language :: Python :: 3.5
Classifier: Programming Language :: Python :: 3.6
Classifier: Topic :: Software Development :: Libraries
Classifier: Topic :: Software Development :: Libraries :: Python Modules
Classifier: Intended Audience :: Developers
Requires-Python: >=3.5
Requires-Dist: requests
